setup.py
Probability_Distributions_Musu/Binomialdistribution.py
Probability_Distributions_Musu/Gaussiandistribution.py
Probability_Distributions_Musu/Generaldistribution.py
Probability_Distributions_Musu/__init__.py
Probability_Distributions_Musu.egg-info/PKG-INFO
Probability_Distributions_Musu.egg-info/SOURCES.txt
Probability_Distributions_Musu.egg-info/dependency_links.txt
Probability_Distributions_Musu.egg-info/not-zip-safe
Probability_Distributions_Musu.egg-info/top_level.txt